{
    "name": "Ĺ̷̢̨̧̧̡̨̨̛͕͖̟̤̳̗̭̬̤͎͇̠̮̩̘͕̤͙̣̲̲̝̝̺̩͎͕͔̳̗̦̣̠̙͇̣̯̫̼͇̉̒̈́͋̉̅̄̍͛̋̏̏̓́͑͛̾͂̈́̏͑̉̂̄̃͐̄̈́̀̊͒̅̕͜͜͠ͅͅͅ1̴̢̛̙̞͈̞̣̥̬̝͕̹͖̺̠̉̽̎̋͆̈́̂̀͑̂͂̀̉͒̏̇̐́͛̄̐̿͒̐̑͌̌̍̆̓͛̔̀̅̋̍̓̄͋͌́́̊̿̈̇̽̈́͌͐͒͒̃͛́̈́̒͂̈́̾̑̽͗̄͆͒̚͘̕͘͘̚͠͝͠͠͝͝#̶̡̨̨̡̹͖̰͙͚̗͓̞̩͕͚̯͔̣̟̗̱̲̺̪͍͎̫̜̗̪̹̤̗͍̲̬̰͍̙̮̖͍̺̝͓̎́̂̈̏͗͂͐̀͗̉̀̒̽̊͑́̓͒̐͑͐̂̓̏̈́̓̿͊̆̾̂͗͗̂͒̓̔̃͑́̄͂̄̑͛̅̏͂̐͆̉̐͘͘̕͜͝͝͝͝͠ͅͅͅ∂̵̢̢̧̧̧̨̢̡͕̠̙̥̻̹̤̙͇̬̳͈̻̭̻̠̙͈̩̖̖̲̣̫̫̯̪͓̩͖̘̩͇̥̳̖̙͚͍̬̹͓͖̫̗̣̖͓̪̞̙͉̻͙̫͚̲̊̿̋̔̒̈́̀̋͂͒̆̇́̑͋͐͊̍̽̋͗̀̕͜͝͝͝ͅͅ⊗̵̪͇́̇͒͊͝0̶̨̧̧͓̖͈̜͈̘̰̫̣̜͖̲̬̮̻̖͕͖͍̰̗̫͍̳͓͙͚̻̙͈̬̘͍̖̜̝̬͖͓̗̘̖͓̟͍̳̜̘̗̘̪̭̠̱̲̲̠̼͔̫̠̖͒̀̃͆̊̾̌̋̀̆̂̽̀̇̽͂̏̓̽̽̍͊͑̍̓̓͐͊̓̋̔̔͒̈́̕̚̕͜͜͝͝",
    "icon": "trepidation:limbo.png",
    "category": "limbo",
    "advancement": "triumph:advancements/dimensions/limbo",
    "pages": [
      {
        "type": "text",
        "text": "$(#551012)This place, it hu$(obf)r$()$(#551012)ts to look at. I can't even begin to $(obf)e$()$(#551012)xplain the pa$(obf)i$()$(#551012)n or where it's located. The ground beneath m$(obf)e$()$(#551012) is a swirling mass, as if the very threads of rea$(obf)l$()$(#551012)ity are coming undone. There’s a sense of pe$(obf)r$()$(#551012)petual motion, yet I stand still, frozen in $(obf)th$()$(#551012)is abyss."
      },
      {
        "type": "text",
        "text": "$(#551012)The air is h$(obf)ea$()$(#551012)vy, pressing in on me from all sides. These... b$(obf)o$()$(#551012)x$(obf)e$()$(#551012)s, with their piercing eyes, all watching me. I only see th$(obf)e$()$(#551012)m as a simple shape, but I can feel a vast p$(obf)r$()$(#551012)esenc$(obf)e$()$(#551012) lurking behind their gaze - a single, immense con$(obf)s$()$(#551012)ciou$(obf)s$()$(#551012)ness I cannot reliably put into words. Their stare penet$(obf)ra$()$(#551012)tes my soul, laying bare every fea$(obf)r$()$(#551012), every $(obf)r$()$(#551012)egret."
      },
      {
        "type": "text",
        "text": "$(#551012)I mus$(obf)t$()$(#551012)er up all my will$(obf)p$()$(#551012)ower and strength to step for$(obf)wa$()$(#551012)rd, but the ground gives way, threate$(obf)nin$()$(#551012)g to swallow me whole, only for it to ins$(obf)t$()$(#551012)antly reappear back to its or$(obf)igi$()$(#551012)nal state. My though$(obf)ts$()$(#551012) are unravel$(obf)i$()$(#551012)ng; I cannot tell $(obf)wa$()$(#551012)at is r$(obf)e$()$(#551012)al and what is not, and w$(obf)he$()$(#551012)ther I've been here for mere seconds or yea$(obf)rs$()$(#551012)."
      },
      {
        "type": "text",
        "text": "$(#551012)\"Ther$(obf)e$()$(#551012) is no escap$(obf)e$()$(#551012),\" I mutter but do not hear my own voice. \"Th$(obf)ere$()$(#551012) i$(obf)s$()$(#551012) no e$(obf)sc$()$(#551012)ap$(obf)e$()$(#551012). $(obf)T$()$(#551012)he$(obf)re$()$(#551012) is $(obf)n$()$(#551012)o e$(obf)sca$()$(#551012)pe.\" The phrase loops in my $(obf)m$()$(#551012)ind as a mantra, fo$(obf)r$()$(#551012)ci$(obf)b$()$(#551012)ly placed—yet maybe not. I begin to see blur$(obf)ry$()$(#551012) fig$(obf)u$()$(#551012)res in the d$(obf)i$()$(#551012)sta$(obf)n$()$(#551012)ce. I stumbl$(obf)e$()$(#551012) forward with the last bit of $(obf)m$()$(#551012)y ener$(obf)g$()$(#551012)y and sc$(obf)re$()$(#551012)am for hel$(obf)p$()$(#551012), but aga$(obf)i$()$(#551012)n no $(obf)so$()$(#551012)und es$(obf)ea$()$(#551012)pes, not ev$(obf)e$()$(#551012)n fro$(obf)m$()$(#551012) my foo$(obf)tst$()$(#551012)eps."
      },
      {
        "type": "text",
        "text": "$(#551012)I dra$(obf)w$()$(#551012) clos$(obf)er$()$(#551012) an$(br)d real$(obf)i$()$(#551012)ze they ar$(obf)e$()$(#551012) all$(br) $(obf)fr$()$(#551012)ozen in mo$(br)$(obf)m$()$(#551012)en$(br)$(br)ts of de$(br)sp$(obf)a$()$(#551012)ir, fli$(obf)ck$()$(#551012)er$(br)in$(obf)g$()$(#551012) in $(obf)a$()$(#551012)nd out of exi$(obf)s$(br)te$()$(#551012)nce, f$(br)a$(obf)c$()$(#551012)es tw$(obf)is$(br)$()$(#551012)ted in ag$(br)$(obf)o$()$(#551012)n$(obf)y$()$(#551012), eye so$(br)$(br)c$(obf)ke$()$(#551012)ts$(br)$(br) e$(obf)m$()$(#551012)p$(obf)t$()$(#551012)y."
      },
      {
        "type": "text",
        "text": "$(#551012)I turn to look behind me, and terror fills my being.$(br2)My body never moved.$(br2)Th$(obf)e$()$(#551012)re is no e$(obf)s$()$(#551012)cape. Th$(obf)er$()$(#551012)e is n$(obf)o$()$(#551012) esca$(obf)p$()$(#551012)e. Th$(obf)ere$()$(#551012) $(obf)is$()$(#551012) no $(obf)esca$()$(#551012)p$(obf)e$()$(#551012). $(obf)There$()$(#551012)e i$(obf)s$()$(#551012) n$(obf)o$()$(#551012) $(obf)escape. There is no escape. There is no escape. There is no escape. There is no escape. There is no escape. There is no escape. There is no escape. There is no escape. There is no escape. There is no escape. There is no escape. There is no escape. There is no escape. There is no escape. There is no escape. There is no escape. There is no escape. There is no escape. There is no escape. There is no escape. There is no escape. There is no escape. There is no escape. There is no escape. There is no escape. There is no escape. There is no escape. There is no escape. There is no escape. There is no escape. $()$(#551012)$()"
      }
      
    ]
  }